momotor/shared/__init__.py
momotor/shared/doc.py
momotor/shared/exlock.py
momotor/shared/lockset.py
momotor/shared/log.py
momotor/shared/resources/__init__.py
momotor/shared/resources/const.py
momotor/shared/resources/exception.py
momotor/shared/resources/group.py
momotor/shared/resources/item.py
momotor/shared/resources/tag.py
momotor/shared/resources/utils.py
momotor/shared/state/__init__.py
momotor/shared/state/base.py
momotor/shared/state/exception.py
momotor/shared/state/local.py
momotor_engine_shared-2.1.0.dist-info/METADATA
momotor_engine_shared-2.1.0.dist-info/WHEEL
momotor_engine_shared-2.1.0.dist-info/top_level.txt
momotor_engine_shared-2.1.0.dist-info/RECORD
